{"array":{"bun":"3","node":"2","deno":"6","graaljs":"26","hermes":"","llrt":"8","txiki.js":"5","quickjs":"6","quickjs-ng":"5","mujs":"17","xst":"","JavaScriptCore":"","v8":"8","spidermonkey":"6","JerryScript":"","primjs":"6","rquickjs":"8","duktape":"20","nova":"","engine262":"[object Object]","ladybird":"7","goja":"","kiesel":"72","mozjs":"","jint":"72","dune":"\u001b[33m6\u001b[0m","jjs":"","rhino":"","njs":"3","ringo":"146","spiderfire":"4","hako":"200","quickjs-emscripten":"24"},"loop":{"bun":"2","node":"11","deno":"10","graaljs":"21","hermes":"","llrt":"298","txiki.js":"150","quickjs":"15","quickjs-ng":"174","mujs":"1296","xst":"","JavaScriptCore":"","v8":"9","spidermonkey":"4","JerryScript":"","primjs":"5","rquickjs":"150","duktape":"945","nova":"","engine262":"[object Object]","ladybird":"5","goja":"","kiesel":"2170","mozjs":"","jint":"58","dune":"\u001b[33m9\u001b[0m","jjs":"","rhino":"","njs":"1643","ringo":"42","spiderfire":"4","hako":"185","quickjs-emscripten":"1786"}}
